taskio/__init__.py
taskio/config.py
taskio/core.py
taskio/decorators.py
taskio/process.py
taskio-0.0.7.dist-info/LICENSE
taskio-0.0.7.dist-info/METADATA
taskio-0.0.7.dist-info/WHEEL
taskio-0.0.7.dist-info/top_level.txt
taskio-0.0.7.dist-info/RECORD
